{
  "parent": "minecraft:recipes/root",
  "rewards": {
    "recipes": [
      "colorful_journey:metal/colored_red_ingots_from_smelting_nether"
    ]
  },
  "criteria": {
    "has_item": {
      "trigger": "minecraft:inventory_changed",
      "conditions": {
        "items": [
          {
            "item": "colorful_journey:colored_nether_ore_red"
          }
        ]
      }
    },
    "has_the_recipe": {
      "trigger": "minecraft:recipe_unlocked",
      "conditions": {
        "recipe": "colorful_journey:metal/colored_red_ingots_from_smelting_nether"
      }
    }
  },
  "requirements": [
    [
      "has_item",
      "has_the_recipe"
    ]
  ]
}